Workbook

Sheet Maintain
E1: Make changes in Blue highlight | I1: password for maintain sheet : 1234
C2: Cost Sheet | L2: Date | M2: 44509
C3: PO no | G3: Plant | K3: =IFERROR(__xludf.DUMMYFUNCTION("GOOGLEFINANCE(K4)"),81.6395) -> 81.6395 | L3: Revised date
C4: Contract date | G4: Exc Rate | H4: as of | J4: =IFERROR(__xludf.DUMMYFUNCTION("GOOGLEFINANCE(K4)"),81.6395) -> 81.6395 | K4: USDINR
C5: Customer | D5: Malyasia
C6: COUNTRY | D6: USA | G6: PORT OF LOADING / Date
C7: INCOTERM | G7: PORT OF DESTINATION / Date | L7: Prepare | N7: Verify | P7: Approve
C8: PAYMENT
C9: Sell information | E9: PROUDCT Code (< 18 digits) | F9: Product name (< 40 digits) | H9: size | I9: pack | J9: Weight | K9: @ USD | L9: 000 USD | M9: 000INR | N9: @ INR | O9: Stock FG KG. | P9: cost @ INR
A10: 0825GC105020L1620P | D10: 1 | E10: 0825GC105020L1620P | F10: =IFERROR(VLOOKUP(E10,master!$B:$H,3,FALSE),0) -> VA PDTO IQF T NB 16/20 5X2LB | H10: =IFERROR(VLOOKUP(E10,master!$B:$H,7,FALSE),0) -> 16/20 | I10: 5X2LBS | J10: 50000 | K10: 10.2 | L10: =K10*J10/1000 -> 510 | M10: =$J$4*L10 -> 41636.145 | N10: =IFERROR(M10/J10*1000,0) -> 832.7229 | O10: 5
A11: 0825GC105020L2125P | D11: 2 | E11: 0825GC105020L2125P | F11: =IFERROR(VLOOKUP(E11,master!$B:$H,3,FALSE),0) -> VA PDTO IQF T NB 21/25 5X2LB | H11: =IFERROR(VLOOKUP(E11,master!$B:$H,7,FALSE),0) -> 21/25 | I11: 5X2LBS | J11: 40000 | K11: 7.7 | L11: =K11*J11/1000 -> 308 | M11: =$J$4*L11 -> 25144.966 | N11: =IFERROR(M11/J11*1000,0) -> 628.62415 | O11: 3.5
A12: 0826VC105020L2630P | D12: 3 | E12: 0825GC105020L2630P | F12: =IFERROR(VLOOKUP(E12,master!$B:$H,3,FALSE),0) -> VA PDTO IQF T NB 26/30 5X2LB | H12: =IFERROR(VLOOKUP(E12,master!$B:$H,7,FALSE),0) -> 26/30 | I12: 5X2LBS | J12: 20000 | K12: 6.8 | L12: =K12*J12/1000 -> 136 | M12: =$J$4*L12 -> 11102.972 | N12: =IFERROR(M12/J12*1000,0) -> 555.1486 | O12: 4
D13: 4 | E13: 0826VC105020L2125P | F13: =IFERROR(VLOOKUP(E13,master!$B:$H,3,FALSE),0) -> VA PDTL IQF T NB 21/25 5X2LB | H13: =IFERROR(VLOOKUP(E13,master!$B:$H,7,FALSE),0) -> 21/25 | I13: 5X2LBS | J13: 20000 | K13: 7.7 | L13: =K13*J13/1000 -> 154 | M13: =$J$4*L13 -> 12572.483 | N13: =IFERROR(M13/J13*1000,0) -> 628.62415 | O13: 3.2
D14: 5 | E14: 0826VC105020L2630P | F14: =IFERROR(VLOOKUP(E14,master!$B:$H,3,FALSE),0) -> VA PDTL IQF T NB 26/30 5X2LB | H14: =IFERROR(VLOOKUP(E14,master!$B:$H,7,FALSE),0) -> 26/30 | I14: 5X2LBS | J14: 20000 | K14: 6.8 | L14: =K14*J14/1000 -> 136 | M14: =$J$4*L14 -> 11102.972 | N14: =IFERROR(M14/J14*1000,0) -> 555.1486 | O14: 3
D15: 6 | E15: 0826VC105020L3140P | F15: =IFERROR(VLOOKUP(E15,master!$B:$H,3,FALSE),0) -> VA PDTL IQF T NB 31/40 5X2LB | H15: =IFERROR(VLOOKUP(E15,master!$B:$H,7,FALSE),0) -> 31/40 | I15: 5X2LBS | J15: 130000 | K15: 6.2 | L15: =K15*J15/1000 -> 806 | M15: =$J$4*L15 -> 65801.437 | N15: =IFERROR(M15/J15*1000,0) -> 506.1649 | O15: 3
D16: 7 | E16: 0826VC105020L4150P | F16: =IFERROR(VLOOKUP(E16,master!$B:$H,3,FALSE),0) -> VA PDTL IQF T NB 41/50 5X2LB | H16: =IFERROR(VLOOKUP(E16,master!$B:$H,7,FALSE),0) -> 41/50 | I16: 5X2LBS | J16: 110000 | K16: 5.9 | L16: =K16*J16/1000 -> 649 | M16: =$J$4*L16 -> 52984.035 | N16: =IFERROR(M16/J16*1000,0) -> 481.67305 | O16: 3
D17: 8 | E17: 0826VC105020L5160P | F17: =IFERROR(VLOOKUP(E17,master!$B:$H,3,FALSE),0) -> VA PDTL IQF T NB 51/60 5X2LB | H17: =IFERROR(VLOOKUP(E17,master!$B:$H,7,FALSE),0) -> 51/60 | I17: 5X2LBS | J17: 40000 | K17: 5.2 | L17: =K17*J17/1000 -> 208 | M17: =$J$4*L17 -> 16981.016 | N17: =IFERROR(M17/J17*1000,0) -> 424.5254
D18: 9 | E18: 0826VC105020L6170P | F18: =IFERROR(VLOOKUP(E18,master!$B:$H,3,FALSE),0) -> VA PDTL IQF T NB 61/70 5X2LB | H18: =IFERROR(VLOOKUP(E18,master!$B:$H,7,FALSE),0) -> 61/70 | I18: 5X2LBS | J18: 20000 | K18: 4.7 | L18: =K18*J18/1000 -> 94 | M18: =$J$4*L18 -> 7674.113 | N18: =IFERROR(M18/J18*1000,0) -> 383.70565
D19: 10 | F19: =IFERROR(VLOOKUP(E19,master!$B:$H,3,FALSE),0) -> 0 | H19: =IFERROR(VLOOKUP(E19,master!$B:$H,7,FALSE),0) -> 0 | L19: =K19*J19/1000 -> 0 | M19: =$J$4*L19 -> 0 | N19: =IFERROR(M19/J19*1000,0) -> 0
D20: 11 | F20: =IFERROR(VLOOKUP(E20,master!$B:$H,3,FALSE),0) -> 0 | H20: =IFERROR(VLOOKUP(E20,master!$B:$H,7,FALSE),0) -> 0 | L20: =K20*J20/1000 -> 0 | M20: =$J$4*L20 -> 0 | N20: =IFERROR(M20/J20*1000,0) -> 0
D21: 12 | F21: =IFERROR(VLOOKUP(E21,master!$B:$H,3,FALSE),0) -> 0 | H21: =IFERROR(VLOOKUP(E21,master!$B:$H,7,FALSE),0) -> 0 | L21: =K21*J21/1000 -> 0 | M21: =$J$4*L21 -> 0 | N21: =IFERROR(M21/J21*1000,0) -> 0
I22: Total | J22: =SUM(J10:J21) -> 450000 | K22: =L22/J22*1000 -> 6.6688889 | L22: =SUM(L10:L21) -> 3001 | M22: =SUM(M10:M21) -> 245000.14 | N22: =M22/J22*1000 -> 544.44475
C24: Description | E24: 1 | F24: 2 | G24: 3 | H24: 4 | I24: 5 | J24: 6 | K24: 7 | L24: 8 | M24: 9 | N24: 10 | O24: 11 | P24: 12 | Q24: Total
C25: Product Name | E25: =IFERROR(VLOOKUP(E24,$D$10:$F$21,3,FALSE),"n/a") -> VA PDTO IQF T NB 16/20 5X2LB | F25: =IFERROR(VLOOKUP(F24,$D$10:$F$21,3,FALSE),"n/a") -> VA PDTO IQF T NB 21/25 5X2LB | G25: =IFERROR(VLOOKUP(G24,$D$10:$F$21,3,FALSE),"n/a") -> VA PDTO IQF T NB 26/30 5X2LB | H25: =IFERROR(VLOOKUP(H24,$D$10:$F$21,3,FALSE),"n/a") -> VA PDTL IQF T NB 21/25 5X2LB | I25: =IFERROR(VLOOKUP(I24,$D$10:$F$21,3,FALSE),"n/a") -> VA PDTL IQF T NB 26/30 5X2LB | J25: =IFERROR(VLOOKUP(J24,$D$10:$F$21,3,FALSE),"n/a") -> VA PDTL IQF T NB 31/40 5X2LB | K25: =IFERROR(VLOOKUP(K24,$D$10:$F$21,3,FALSE),"n/a") -> VA PDTL IQF T NB 41/50 5X2LB | L25: =IFERROR(VLOOKUP(L24,$D$10:$F$21,3,FALSE),"n/a") -> VA PDTL IQF T NB 51/60 5X2LB | ... P25: =IFERROR(VLOOKUP(P24,$D$10:$F$21,3,FALSE),"n/a") -> 0
C26: Product code | E26: =VLOOKUP(E24,$D$10:$E$21,2,FALSE) -> 0825GC105020L1620P | F26: =VLOOKUP(F24,$D$10:$E$21,2,FALSE) -> 0825GC105020L2125P | G26: =VLOOKUP(G24,$D$10:$E$21,2,FALSE) -> 0825GC105020L2630P | H26: =VLOOKUP(H24,$D$10:$E$21,2,FALSE) -> 0826VC105020L2125P | I26: =VLOOKUP(I24,$D$10:$E$21,2,FALSE) -> 0826VC105020L2630P | J26: =VLOOKUP(J24,$D$10:$E$21,2,FALSE) -> 0826VC105020L3140P | K26: =VLOOKUP(K24,$D$10:$E$21,2,FALSE) -> 0826VC105020L4150P | L26: =VLOOKUP(L24,$D$10:$E$21,2,FALSE) -> 0826VC105020L5160P | ... P26: =VLOOKUP(P24,$D$10:$E$21,2,FALSE) -> 0
C27: KG | E27: =IFERROR(VLOOKUP(E24,$D$10:$J$21,7,FALSE),0) -> 50000 | F27: =IFERROR(VLOOKUP(F24,$D$10:$J$21,7,FALSE),0) -> 40000 | G27: =IFERROR(VLOOKUP(G24,$D$10:$J$21,7,FALSE),0) -> 20000 | H27: =IFERROR(VLOOKUP(H24,$D$10:$J$21,7,FALSE),0) -> 20000 | I27: =IFERROR(VLOOKUP(I24,$D$10:$J$21,7,FALSE),0) -> 20000 | J27: =IFERROR(VLOOKUP(J24,$D$10:$J$21,7,FALSE),0) -> 130000 | K27: =IFERROR(VLOOKUP(K24,$D$10:$J$21,7,FALSE),0) -> 110000 | L27: =IFERROR(VLOOKUP(L24,$D$10:$J$21,7,FALSE),0) -> 40000 | ... P27: =IFERROR(VLOOKUP(P24,$D$10:$J$21,7,FALSE),0) -> 0 | Q27: =SUM(E27:P27) -> 450000
C28: Yield | E28: =IFERROR(VLOOKUP(E26,master!$B:$H,6,FALSE),0) -> 0.63 | F28: =IFERROR(VLOOKUP(F26,master!$B:$H,6,FALSE),0) -> 0.63 | G28: =IFERROR(VLOOKUP(G26,master!$B:$H,6,FALSE),0) -> 0.63 | H28: =IFERROR(VLOOKUP(H26,master!$B:$H,6,FALSE),0) -> 0.63 | I28: =IFERROR(VLOOKUP(I26,master!$B:$H,6,FALSE),0) -> 0.63 | J28: =IFERROR(VLOOKUP(J26,master!$B:$H,6,FALSE),0) -> 0.63 | K28: =IFERROR(VLOOKUP(K26,master!$B:$H,6,FALSE),0) -> 0.63 | L28: =IFERROR(VLOOKUP(L26,master!$B:$H,6,FALSE),0) -> 0.63 | ... P28: =IFERROR(VLOOKUP(P26,master!$B:$H,6,FALSE),0) -> 0 | Q28: =Q27/Q30 -> 0.63
C29: AVG size | E29: =IFERROR(VLOOKUP(E26,master!$B:$H,5,FALSE),0) -> 27 | F29: =IFERROR(VLOOKUP(F26,master!$B:$H,5,FALSE),0) -> 34 | G29: =IFERROR(VLOOKUP(G26,master!$B:$H,5,FALSE),0) -> 41 | H29: =IFERROR(VLOOKUP(H26,master!$B:$H,5,FALSE),0) -> 33 | I29: =IFERROR(VLOOKUP(I26,master!$B:$H,5,FALSE),0) -> 40 | J29: =IFERROR(VLOOKUP(J26,master!$B:$H,5,FALSE),0) -> 47 | K29: =IFERROR(VLOOKUP(K26,master!$B:$H,5,FALSE),0) -> 64 | L29: =IFERROR(VLOOKUP(L26,master!$B:$H,5,FALSE),0) -> 78 | ... P29: =IFERROR(VLOOKUP(P26,master!$B:$H,5,FALSE),0) -> 0 | Q29: =Q31/Q30 -> 51.022222
C30: RM Usage KG | E30: =IFERROR(E27/E28,0) -> 79365.079 | F30: =IFERROR(F27/F28,0) -> 63492.063 | G30: =IFERROR(G27/G28,0) -> 31746.032 | H30: =IFERROR(H27/H28,0) -> 31746.032 | I30: =IFERROR(I27/I28,0) -> 31746.032 | J30: =IFERROR(J27/J28,0) -> 206349.21 | K30: =IFERROR(K27/K28,0) -> 174603.17 | L30: =IFERROR(L27/L28,0) -> 63492.063 | ... P30: =IFERROR(P27/P28,0) -> 0 | Q30: =SUM(E30:P30) -> 714285.71
C31: PCs | E31: =IFERROR(E29*E30,0) -> 2142857.1 | F31: =IFERROR(F29*F30,0) -> 2158730.2 | G31: =IFERROR(G29*G30,0) -> 1301587.3 | H31: =IFERROR(H29*H30,0) -> 1047619 | I31: =IFERROR(I29*I30,0) -> 1269841.3 | J31: =IFERROR(J29*J30,0) -> 9698412.7 | K31: =IFERROR(K29*K30,0) -> 11174603 | L31: =IFERROR(L29*L30,0) -> 4952381 | ... P31: =IFERROR(P29*P30,0) -> 0 | Q31: =SUM(E31:P31) -> 36444444
C32: RM Price | D32: =IF(M3=0,M2,M3) -> 44509 | E32: =490*0.95 -> 465.5 | F32: =340*0.95 -> 323 | G32: =290*0.95 -> 275.5 | H32: =344*0.95 -> 326.8 | I32: =294*0.95 -> 279.3 | J32: =264*0.95 -> 250.8 | K32: =244*0.95 -> 231.8 | L32: =214*0.95 -> 203.3 | M32: =190*0.95 -> 180.5 | Q32: =SUMPRODUCT(E30:P30,E32:P32)/Q30 -> 274.82444
C33: Selling price RS/kg | E33: =IFERROR(VLOOKUP(E24,$D$10:$N$21,11,FALSE),"n/a") -> 832.7229 | F33: =IFERROR(VLOOKUP(F24,$D$10:$N$21,11,FALSE),"n/a") -> 628.62415 | G33: =IFERROR(VLOOKUP(G24,$D$10:$N$21,11,FALSE),"n/a") -> 555.1486 | H33: =IFERROR(VLOOKUP(H24,$D$10:$N$21,11,FALSE),"n/a") -> 628.62415 | I33: =IFERROR(VLOOKUP(I24,$D$10:$N$21,11,FALSE),"n/a") -> 555.1486 | J33: =IFERROR(VLOOKUP(J24,$D$10:$N$21,11,FALSE),"n/a") -> 506.1649 | K33: =IFERROR(VLOOKUP(K24,$D$10:$N$21,11,FALSE),"n/a") -> 481.67305 | L33: =IFERROR(VLOOKUP(L24,$D$10:$N$21,11,FALSE),"n/a") -> 424.5254 | ... P33: =IFERROR(VLOOKUP(P24,$D$10:$N$21,11,FALSE),"n/a") -> 0 | Q33: =M22/J22*1000 -> 544.44475
E34: Cost | F34: Cost | G34: Cost | H34: Cost | I34: Cost | J34: Cost | K34: Cost | L34: Cost | M34: Cost | N34: Cost | O34: Cost | P34: Cost
C35: Variable cost
C36: Stock cost | E36: =IFERROR(VLOOKUP(E24,$D$10:$P$21,12,FALSE),"n/a") -> 5 | F36: =IFERROR(VLOOKUP(F24,$D$10:$P$21,12,FALSE),"n/a") -> 3.5 | G36: =IFERROR(VLOOKUP(G24,$D$10:$P$21,12,FALSE),"n/a") -> 4 | H36: =IFERROR(VLOOKUP(H24,$D$10:$P$21,12,FALSE),"n/a") -> 3.2 | I36: =IFERROR(VLOOKUP(I24,$D$10:$P$21,12,FALSE),"n/a") -> 3 | J36: =IFERROR(VLOOKUP(J24,$D$10:$P$21,12,FALSE),"n/a") -> 3 | K36: =IFERROR(VLOOKUP(K24,$D$10:$P$21,12,FALSE),"n/a") -> 3 | L36: =IFERROR(VLOOKUP(L24,$D$10:$P$21,12,FALSE),"n/a") -> 0 | ... P36: =IFERROR(VLOOKUP(P24,$D$10:$P$21,12,FALSE),"n/a") -> 0
C37: Raw material meat | E37: =IF(E28>0,(E32+2)/E28,0) -> 742.06349 | F37: =IF(F28>0,(F32+2)/F28,0) -> 515.87302 | G37: =IF(G28>0,(G32+2)/G28,0) -> 440.47619 | H37: =IF(H28>0,(H32+2)/H28,0) -> 521.90476 | I37: =IF(I28>0,(I32+2)/I28,0) -> 446.50794 | J37: =IF(J28>0,(J32+2)/J28,0) -> 401.26984 | K37: =IF(K28>0,(K32+2)/K28,0) -> 371.11111 | L37: =IF(L28>0,(L32+2)/L28,0) -> 325.87302 | ... P37: =IF(P28>0,(P32+2)/P28,0) -> 0 | Q37: =SUMPRODUCT(E27:P27,E37:P37)/Q27 -> 439.40388
C38: Packaging (Include re-pack) | E38: 8 | F38: 8 | G38: 8 | H38: 8 | I38: 8 | J38: 8 | K38: 8 | Q38: =SUMPRODUCT(E27:P27,E38:P38)/Q27 -> 6.9333333
C39: Additive | E39: 6.5 | F39: 6.5 | G39: 6.5 | H39: 6.5 | I39: 6.5 | J39: 6.5 | K39: 6.5 | Q39: =SUMPRODUCT(E27:P27,E39:P39)/Q27 -> 5.6333333
C40: Harvesting | E40: =IF(E27=0,0,1/E28*9.9) -> 15.714286 | F40: =IF(F27=0,0,1/F28*9.9) -> 15.714286 | G40: =IF(G27=0,0,1/G28*9.9) -> 15.714286 | H40: =IF(H27=0,0,1/H28*9.9) -> 15.714286 | I40: =IF(I27=0,0,1/I28*9.9) -> 15.714286 | J40: =IF(J27=0,0,1/J28*9.9) -> 15.714286 | K40: =IF(K27=0,0,1/K28*9.9) -> 15.714286 | L40: =IF(L27=0,0,1/L28*9.9) -> 15.714286 | ... P40: =IF(P27=0,0,1/P28*9.9) -> 0 | Q40: =SUMPRODUCT(E27:P27,E40:P40)/Q27 -> 15.714286
C41: Processing charge | Q41: =SUMPRODUCT(E27:P27,E41:P41)/Q27 -> 0
C42: Commission | F42: =IF(F$27>0,$E42,0) -> 0 | G42: =IF(G$27>0,$E42,0) -> 0 | H42: =IF(H$27>0,$E42,0) -> 0 | I42: =IF(I$27>0,$E42,0) -> 0 | J42: =IF(J$27>0,$E42,0) -> 0 | K42: =IF(K$27>0,$E42,0) -> 0 | L42: =IF(L$27>0,$E42,0) -> 0 | M42: =IF(M$27>0,$E42,0) -> 0 | ... P42: =IF(P$27>0,$E42,0) -> 0 | Q42: =SUMPRODUCT(E27:P27,E42:P42)/Q27 -> 0
C43: Export shipment | E43: 25 | F43: =IF(F$27>0,$E43,0) -> 25 | G43: =IF(G$27>0,$E43,0) -> 25 | H43: =IF(H$27>0,$E43,0) -> 25 | I43: =IF(I$27>0,$E43,0) -> 25 | J43: =IF(J$27>0,$E43,0) -> 25 | K43: =IF(K$27>0,$E43,0) -> 25 | L43: =IF(L$27>0,$E43,0) -> 25 | M43: =IF(M$27>0,$E43,0) -> 25 | ... P43: =IF(P$27>0,$E43,0) -> 0 | Q43: =SUMPRODUCT(E27:P27,E43:P43)/Q27 -> 25
C44: Clearance at destination port (DDP) | E44: 0 | F44: =IF(F$27>0,$E44,0) -> 0 | G44: =IF(G$27>0,$E44,0) -> 0 | H44: =IF(H$27>0,$E44,0) -> 0 | I44: =IF(I$27>0,$E44,0) -> 0 | J44: =IF(J$27>0,$E44,0) -> 0 | K44: =IF(K$27>0,$E44,0) -> 0 | L44: =IF(L$27>0,$E44,0) -> 0 | M44: =IF(M$27>0,$E44,0) -> 0 | ... P44: =IF(P$27>0,$E44,0) -> 0 | Q44: =SUMPRODUCT(E27:P27,E44:P44)/Q27 -> 0
C45: DBK&MEIS : DBK | D45: 0.03 | E45: =-E33*98%*$D45 -> -24.482053 | F45: =-F33*98%*$D45 -> -18.48155 | G45: =-G33*98%*$D45 -> -16.321369 | H45: =-H33*98%*$D45 -> -18.48155 | I45: =-I33*98%*$D45 -> -16.321369 | J45: =-J33*98%*$D45 -> -14.881248 | K45: =-K33*98%*$D45 -> -14.161188 | L45: =-L33*98%*$D45 -> -12.481047 | ... P45: =-P33*98%*$D45 -> 0 | Q45: =SUMPRODUCT(E27:P27,E45:P45)/Q27 -> -16.006676 | R45: New*
C46: : MEIS | D46: 0.025 | E46: =-E33*98%*$D46 -> -20.401711 | F46: =-F33*98%*$D46 -> -15.401292 | G46: =-G33*98%*$D46 -> -13.601141 | H46: =-H33*98%*$D46 -> -15.401292 | I46: =-I33*98%*$D46 -> -13.601141 | J46: =-J33*98%*$D46 -> -12.40104 | K46: =-K33*98%*$D46 -> -11.80099 | L46: =-L33*98%*$D46 -> -10.400872 | ... P46: =-P33*98%*$D46 -> 0 | Q46: =SUMPRODUCT(E27:P27,E46:P46)/Q27 -> -13.338896 | R46: New*
C47: Variable cost total | E47: =SUM(E37:E46) -> 752.39401 | F47: =SUM(F37:F46) -> 537.20446 | G47: =SUM(G37:G46) -> 465.76797 | H47: =SUM(H37:H46) -> 543.23621 | I47: =SUM(I37:I46) -> 471.79971 | J47: =SUM(J37:J46) -> 429.20184 | K47: =SUM(K37:K46) -> 400.36322 | L47: =SUM(L37:L46) -> 343.70538 | ... Q47: =SUM(Q37:Q46) -> 463.33926
C48: Contrubution Margin @ | D48: Rs./KG | E48: =E33-E47 -> 80.328887 | F48: =F33-F47 -> 91.41969 | G48: =G33-G47 -> 89.380633 | H48: =H33-H47 -> 85.387944 | I48: =I33-I47 -> 83.348887 | J48: =J33-J47 -> 76.963061 | K48: =K33-K47 -> 81.309831 | L48: =L33-L47 -> 80.820017 | ... Q48: =Q33-Q47 -> 81.105494
C49: Contrubution Profit (Loss) 000 Rs. | E49: =E48*E27/1000 -> 4016.4443 | F49: =F48*F27/1000 -> 3656.7876 | G49: =G48*G27/1000 -> 1787.6127 | H49: =H48*H27/1000 -> 1707.7589 | I49: =I48*I27/1000 -> 1666.9777 | J49: =J48*J27/1000 -> 10005.198 | K49: =K48*K27/1000 -> 8944.0814 | L49: =L48*L27/1000 -> 3232.8007 | ... P49: =P48*P27/1000 -> 0 | Q49: =SUM(E49:P49) -> 36497.472
E50: =IFERROR(E48/E33,0) -> 0.096465327 | F50: =IFERROR(F48/F33,0) -> 0.14542822 | G50: =IFERROR(G48/G33,0) -> 0.16100308 | H50: =IFERROR(H48/H33,0) -> 0.13583306 | I50: =IFERROR(I48/I33,0) -> 0.15013798 | J50: =IFERROR(J48/J33,0) -> 0.15205136 | K50: =IFERROR(K48/K33,0) -> 0.1688071 | L50: =IFERROR(L48/L33,0) -> 0.19037734 | ... Q50: =IFERROR(Q48/Q33,0) -> 0.14896919
C51: Fixed cost
C52: Processing charge | E52: 70 | F52: 70 | G52: 70 | H52: 70 | I52: 70 | J52: 70 | K52: 70 | L52: 70 | M52: 70 | N52: 80 | O52: 80 | P52: 80 | Q52: 80
C53: Wage&Salaries | E53: 4.9632111 | F53: =IF(F$27>0,$E$53,0) -> 4.9632111 | G53: =IF(G$27>0,$E$53,0) -> 4.9632111 | H53: =IF(H$27>0,$E$53,0) -> 4.9632111 | I53: =IF(I$27>0,$E$53,0) -> 4.9632111 | J53: =IF(J$27>0,$E$53,0) -> 4.9632111 | K53: =IF(K$27>0,$E$53,0) -> 4.9632111 | L53: =IF(L$27>0,$E$53,0) -> 4.9632111 | M53: =IF(M$27>0,$E$53,0) -> 4.9632111 | ... P53: =IF(P$27>0,$E$53,0) -> 0 | Q53: =SUMPRODUCT($E$27:$P$27,E53:P53)/$Q$27 -> 4.9632111
C54: Rental&Insurance&Other | E54: 0 | F54: =IF(F$27>0,$E$54,0) -> 0 | G54: =IF(G$27>0,$E$54,0) -> 0 | H54: =IF(H$27>0,$E$54,0) -> 0 | I54: =IF(I$27>0,$E$54,0) -> 0 | J54: =IF(J$27>0,$E$54,0) -> 0 | K54: =IF(K$27>0,$E$54,0) -> 0 | L54: =IF(L$27>0,$E$54,0) -> 0 | M54: =IF(M$27>0,$E$54,0) -> 0 | ... P54: =IF(P$27>0,$E$54,0) -> 0 | Q54: =SUMPRODUCT($E$27:$P$27,E54:P54)/$Q$27 -> 0
C55: Depreciation | E55: 0.11407891 | F55: =IF(F$27>0,$E$55,0) -> 0.11407891 | G55: =IF(G$27>0,$E$55,0) -> 0.11407891 | H55: =IF(H$27>0,$E$55,0) -> 0.11407891 | I55: =IF(I$27>0,$E$55,0) -> 0.11407891 | J55: =IF(J$27>0,$E$55,0) -> 0.11407891 | K55: =IF(K$27>0,$E$55,0) -> 0.11407891 | L55: =IF(L$27>0,$E$55,0) -> 0.11407891 | M55: =IF(M$27>0,$E$55,0) -> 0.11407891 | ... P55: =IF(P$27>0,$E$55,0) -> 0 | Q55: =SUMPRODUCT($E$27:$P$27,E55:P55)/$Q$27 -> 0.11407891
C56: Fixed cost total | E56: =SUM(E52:E55) -> 75.07729 | F56: =SUM(F52:F55) -> 75.07729 | G56: =SUM(G52:G55) -> 75.07729 | H56: =SUM(H52:H55) -> 75.07729 | I56: =SUM(I52:I55) -> 75.07729 | J56: =SUM(J52:J55) -> 75.07729 | K56: =SUM(K52:K55) -> 75.07729 | L56: =SUM(L52:L55) -> 75.07729 | ... Q56: =SUM(Q52:Q55) -> 85.07729
C57: Total cost | E57: =E47+E56 -> 827.4713 | F57: =F47+F56 -> 612.28175 | G57: =G47+G56 -> 540.84526 | H57: =H47+H56 -> 618.3135 | I57: =I47+I56 -> 546.877 | J57: =J47+J56 -> 504.27913 | K57: =K47+K56 -> 475.44051 | L57: =L47+L56 -> 418.78267 | ... Q57: =Q47+Q56 -> 548.41655
C58: Profit (Loss) before Admin&Selling Exp fixed @ | E58: =E33-E57 -> 5.2515965 | F58: =F33-F57 -> 16.3424 | G58: =G33-G57 -> 14.303343 | H58: =H33-H57 -> 10.310654 | I58: =I33-I57 -> 8.2715973 | J58: =J33-J57 -> 1.8857711 | K58: =K33-K57 -> 6.2325405 | L58: =L33-L57 -> 5.7427275 | ... Q58: =Q33-Q57 -> -3.9717958
C59: Profit (Loss) before Admin&Selling Exp fixed | E59: =E58*E27/1000 -> 262.57983 | F59: =F58*F27/1000 -> 653.696 | G59: =G58*G27/1000 -> 286.06687 | H59: =H58*H27/1000 -> 206.21308 | I59: =I58*I27/1000 -> 165.43195 | J59: =J58*J27/1000 -> 245.15024 | K59: =K58*K27/1000 -> 685.57946 | L59: =L58*L27/1000 -> 229.7091 | ... P59: =P58*P27/1000 -> 0 | Q59: =SUM(E59:P59) -> 2712.6919
E60: =IFERROR(E58/E33,0) -> 0.0063065355 | F60: =IFERROR(F58/F33,0) -> 0.025997092 | G60: =IFERROR(G58/G33,0) -> 0.025764891 | H60: =IFERROR(H58/H33,0) -> 0.016401938 | I60: =IFERROR(I58/I33,0) -> 0.01489979 | J60: =IFERROR(J58/J33,0) -> 0.0037256062 | K60: =IFERROR(K58/K33,0) -> 0.012939359 | L60: =IFERROR(L58/L33,0) -> 0.013527406 | ... Q60: =IFERROR(Q58/Q33,0) -> -0.0072951309
C61: Remark
C62: Exclude : Admin Exp
C63: Selling Exp fixed
C64: Cap 900 tones

Sheet Processing charge
B2: Processing Charge | D2: 2020 | H2: A | I2: B | J2: C | K2: D | L2: =(B+C+D)xA
I3: Pre-processing | K3: Processing
A4: No. | B4: Plant | C4: Product G | D4: Product | E4: Freeze type | F4: Pack size | G4: Count size | H4: Weight | I4: 1st step: HO=>HL | J4: 2nd step: HL=>Peel | L4: Processing charge/KG | M4: Processing charge/KG +GST
A5: 1 | B5: NELO | C5: HO | D5: HOSO | E5: Block | F5: 1.8Kg/2.0Kg | G5: All size | H5: 1 | K5: 45 | L5: =K5 -> 45 | M5: =L5*1.18 -> 53.1
A6: 2 | B6: NELO | C6: HO | D6: HOSO | E6: Block | F6: 800g/1.0Kg | G6: All size | H6: 1 | K6: 47 | L6: =K6 -> 47 | M6: =L6*1.18 -> 55.46
A7: 3 | B7: NELO | C7: HO | D7: HOSO | E7: Semi IQF | F7: 1.8Kg/2.0Kg | G7: All size | H7: 1 | K7: 45 | L7: =K7 -> 45 | M7: =L7*1.18 -> 53.1
A8: 4 | B8: NELO | C8: HO | D8: HOSO | E8: Semi IQF | F8: 800g/1.0Kg | G8: All size | H8: 1 | K8: 47 | L8: =K8 -> 47 | M8: =L8*1.18 -> 55.46
A9: 5 | B9: NELO | C9: HL | D9: HLSO | E9: Block | F9: 1.8Kg/2.0Kg/4Lbs | G9: All size | H9: 1 | K9: 43 | L9: =K9 -> 43 | M9: =L9*1.18 -> 50.74
A10: 6 | B10: NELO | C10: HL | D10: HLSO | E10: Block | F10: 800g/1.0Kg | G10: All size | H10: 1 | K10: 47 | L10: =K10 -> 47 | M10: =L10*1.18 -> 55.46
A11: 7 | B11: NELO | C11: HL | D11: HL EZ | E11: Block | F11: 1.8Kg/2.0Kg/4Lbs | G11: All size | H11: 1 | K11: 53 | L11: =K11 -> 53 | M11: =L11*1.18 -> 62.54
A12: 8 | B12: NELO | C12: PD | D12: PUD | E12: Block | F12: 1.8Kg/2.0Kg/4Lbs | G12: All size | H12: 1 | K12: 53 | L12: =K12 -> 53 | M12: =L12*1.18 -> 62.54
A13: 9 | B13: NELO | C13: PD | D13: PD | E13: Block | F13: 1.8Kg/2.0Kg/4Lbs | G13: All size | H13: 1 | K13: 53 | L13: =K13 -> 53 | M13: =L13*1.18 -> 62.54
A14: 10 | B14: NELO | C14: PD | D14: PDTO | E14: Block | F14: 1.8Kg/2.0Kg/4Lbs | G14: All size | H14: 1 | K14: 53 | L14: =K14 -> 53 | M14: =L14*1.18 -> 62.54
A15: 11 | B15: NELO | C15: HL | D15: HL EZ | E15: Block | F15: 800g/1.0Kg/1.2Kg | G15: All size | H15: 1 | K15: 55 | L15: =K15 -> 55 | M15: =L15*1.18 -> 64.9
A16: 12 | B16: NELO | C16: PD | D16: PUD | E16: Block | F16: 800g/1.0Kg/1.2Kg | G16: All size | H16: 1 | K16: 55 | L16: =K16 -> 55 | M16: =L16*1.18 -> 64.9
... A34: 30 | B34: NELO | C34: COOK | D34: PDTO | E34: IQF | F34: bulk | G34: All size | H34: 1 | K34: 70 | L34: =K34 -> 70 | M34: =L34*1.18 -> 82.6

Sheet master
B2: Product code | C2: len<20 | D2: Product description by calculation | E2: len<40 | F2: RM avg.size | G2: STD.Yeild % | H2: size | I2: Check
B3: 0826VCI10010K0812P | C3: 18 | D3: VA PDTL IQF T NBFWFC35 8/12 10X1.0KG | E3: 37 | F3: 22 | G3: 0.97 | H3: .8/12 | I3: =VLOOKUP(B3,$K$3:$K$11,1,0) -> #N/A | K3: 0825GC105020L1620P
B4: 0826VCI10010K1315P | C4: 18 | D4: VA PDTL IQF T NBFWFC35 13/15 10X1.0KG | E4: 38 | F4: 31 | G4: 0.97 | H4: 13/15 | I4: =VLOOKUP(B4,$K$3:$K$11,1,0) -> #N/A | K4: 0825GC105020L2125P
B5: 0826VCI10010K1620P | C5: 18 | D5: VA PDTL IQF T NBFWFC35 16/20 10X1.0KG | E5: 38 | F5: 39 | G5: 0.97 | H5: 16/20 | I5: =VLOOKUP(B5,$K$3:$K$11,1,0) -> #N/A | K5: 0825GC105020L2630P
B6: 0826VCI10010K2125P | C6: 18 | D6: VA PDTL IQF T NBFWFC35 21/25 10X1.0KG | E6: 38 | F6: 50 | G6: 0.97 | H6: 21/25 | I6: =VLOOKUP(B6,$K$3:$K$11,1,0) -> #N/A | K6: 0826VC105020L2125P
B7: 0826VCI10010K2630P | C7: 18 | D7: VA PDTL IQF T NBFWFC35 26/30 10X1.0KG | E7: 38 | F7: 61 | G7: 0.97 | H7: 26/30 | I7: =VLOOKUP(B7,$K$3:$K$11,1,0) -> #N/A | K7: 0826VC105020L2630P
B8: 0826VCI10010K3135P | C8: 18 | D8: VA PDTL IQF T NBFWFC35 31/35 10X1.0KG | E8: 38 | F8: 71 | G8: 0.97 | H8: 31/35 | I8: =VLOOKUP(B8,$K$3:$K$11,1,0) -> #N/A | K8: 0826VC105020L3140P
B9: 0826VCI10010K3140P | C9: 18 | D9: VA PDTL IQF T NBFWFC35 31/40 10X1.0KG | E9: 38 | F9: 77 | G9: 0.97 | H9: 31/40 | I9: =VLOOKUP(B9,$K$3:$K$11,1,0) -> #N/A | K9: 0826VC105020L4150P
B10: 0826VCI10010K4150P | C10: 18 | D10: VA PDTL IQF T NBFWFC35 41/50 10X1.0KG | E10: 38 | F10: 98 | G10: 0.97 | H10: 41/50 | I10: =VLOOKUP(B10,$K$3:$K$11,1,0) -> #N/A | K10: 0826VC105020L5160P
B11: 0826VCI10010K5160P | C11: 18 | D11: VA PDTL IQF T NBFWFC35 51/60 10X1.0KG | E11: 38 | F11: 119 | G11: 0.97 | H11: 51/60 | I11: =VLOOKUP(B11,$K$3:$K$11,1,0) -> #N/A | K11: 0826VC105020L6170P
B12: 0826VCI10010K6170P | C12: 18 | D12: VA PDTL IQF T NBFWFC35 61/70 10X1.0KG | E12: 38 | F12: 141 | G12: 0.97 | H12: 61/70 | I12: =VLOOKUP(B12,$K$3:$K$11,1,0) -> #N/A
B13: 0826VCI10010K1115P | C13: 18 | D13: VA PDTL IQF T NBFWFC35 11/15 10X1.0KG | E13: 38 | G13: 0.97 | H13: .11/15 | I13: =VLOOKUP(B13,$K$3:$K$11,1,0) -> #N/A
B14: 0825GCI10010K1115P | C14: 18 | D14: VA PDTO IQF T NBFWFC35 11/15 10X1.0KG | E14: 38 | F14: 30 | G14: 1 | H14: .11/15 | I14: =VLOOKUP(B14,$K$3:$K$11,1,0) -> #N/A
B15: 0825GCI10010K0812P | C15: 18 | D15: VA PDTO IQF T NBFWFC35 8/12 10X1.0KG | E15: 38 | F15: 23 | G15: 1 | H15: .8/12 | I15: =VLOOKUP(B15,$K$3:$K$11,1,0) -> #N/A
B16: 0825GCI10010K1315P | C16: 18 | D16: VA PDTO IQF T NBFWFC35 13/15 10X1.0KG | E16: 38 | F16: 32 | G16: 1 | H16: 13/15 | I16: =VLOOKUP(B16,$K$3:$K$11,1,0) -> #N/A
B17: 0825GCI10010K1620P | C17: 18 | D17: VA PDTO IQF T NBFWFC35 16/20 10X1.0KG | E17: 38 | F17: 41 | G17: 1 | H17: 16/20 | I17: =VLOOKUP(B17,$K$3:$K$11,1,0) -> #N/A
B18: 0825GCI10010K2125P | C18: 18 | D18: VA PDTO IQF T NBFWFC35 21/25 10X1.0KG | E18: 38 | F18: 52 | G18: 1 | H18: 21/25 | I18: =VLOOKUP(B18,$K$3:$K$11,1,0) -> #N/A
B19: 0825GCI10010K2630P | C19: 18 | D19: VA PDTO IQF T NBFWFC35 26/30 10X1.0KG | E19: 38 | F19: 63 | G19: 1 | H19: 26/30 | I19: =VLOOKUP(B19,$K$3:$K$11,1,0) -> #N/A
B20: 0825GCI10010K3135P | C20: 18 | D20: VA PDTO IQF T NBFWFC35 31/35 10X1.0KG | E20: 38 | F20: 74 | G20: 1 | H20: 31/35 | I20: =VLOOKUP(B20,$K$3:$K$11,1,0) -> #N/A
B21: 0825GCI10010K3140P | C21: 18 | D21: VA PDTO IQF T NBFWFC35 31/40 10X1.0KG | E21: 38 | F21: 79 | G21: 1 | H21: 31/40 | I21: =VLOOKUP(B21,$K$3:$K$11,1,0) -> #N/A
B22: 0825GCI10010K4150P | C22: 18 | D22: VA PDTO IQF T NBFWFC35 41/50 10X1.0KG | E22: 38 | F22: 101 | G22: 1 | H22: 41/50 | I22: =VLOOKUP(B22,$K$3:$K$11,1,0) -> #N/A
B23: 0825GCI10010K5160P | C23: 18 | D23: VA PDTO IQF T NBFWFC35 51/60 10X1.0KG | E23: 38 | F23: 123 | G23: 1 | H23: 51/60 | I23: =VLOOKUP(B23,$K$3:$K$11,1,0) -> #N/A
B24: 0825GCI10010K6170P | C24: 18 | D24: VA PDTO IQF T NBFWFC35 61/70 10X1.0KG | E24: 38 | F24: 145 | G24: 1 | H24: 61/70 | I24: =VLOOKUP(B24,$K$3:$K$11,1,0) -> #N/A
B25: 0826VC110020L0812P | C25: 18 | D25: VA PDTL IQF T NB 8/12 10X2LB | E25: 38 | F25: 15 | G25: 0.63 | H25: .08/12 | I25: =VLOOKUP(B25,$K$3:$K$11,1,0) -> #N/A
... B236: 0825GCD10010K4150P | C236: 18 | D236: VA PDTO IQF T NBFWNC35 41/50 10X1.0KG | E236: 36 | F236: 65 | G236: 1 | H236: 41/50 | I236: =VLOOKUP(B236,$K$3:$K$11,1,0) -> #N/A

Sheet Sheet1
A1: PACKER | B1: ITEM | C1: Qty in kgs | D1: QUANTITY | E1: PRICE | F1: Price per kg - Net count frozen weight | G1: Offer price | H1: Volume
A2: KNC Agro | B2: Raw PDTOn 16/20 | C2: =D2*16000 -> 128000 | D2: 8 | E2: 4 | F2: =(E2*2.205*0.9)-0.2 -> 7.738 | G2: 8 | H2: =75000 -> 75000
A3: KNC Agro | B3: Raw PDTOn 26/30 | C3: =D3*16000 -> 160000 | D3: 10 | E3: 3.6 | F3: =(E3*2.205*0.9)-0.2 -> 6.9442 | G3: =F3 -> 6.9442 | H3: 24000
A4: KNC Agro | B4: Raw PDTOff 26/30 | C4: =D4*16000 -> 160000 | D4: 10 | E4: 3.6 | F4: =(E4*2.205*0.9)-0.2 -> 6.9442 | G4: =F4 -> 6.9442 | H4: 16000
A5: KNC Agro | B5: Raw PDTOff 51/60 | C5: =D5*16000 -> 16000 | D5: 1 | E5: 3.1 | F5: =(E5*2.205*0.9)-0.2 -> 5.95195 | G5: 5.4 | H5: 16000
A6: Sandhya Marines | B6: Raw PDTOff 51/60 | C6: =D6*16000 -> 48000 | D6: 3 | E6: 3.25 | F6: =(E6*2.205*0.9)-0.2 -> 6.249625 | G6: 5.4 | H6: 16000
A7: Sharat | B7: Raw PDTOff 51/60 | C7: =D7*16000 -> 64000 | D7: 4 | E7: 3.2 | F7: =(E7*2.205*0.9)-0.2 -> 6.1504 | G7: 5.4 | H7: =C7 -> 64000
A8: Sharat | B8: Raw PDTOn 21/25 | C8: =D8*16000 -> 48000 | D8: 3 | E8: 3.8 | F8: =(E8*2.205*0.9)-0.2 -> 7.3411 | G8: 7.5 | H8: 50000
A9: Sigma | B9: Raw PDToff 41/50 | C9: =D9*16000 -> 0 | F9: 6 | G9: 6 | H9: 140000
A10: Sigma | B10: Raw PDTOff 31/40 | C10: =D10*16000 -> 0 | F10: 6.3 | G10: 6.2 | H10: 120000
I14: check
I15: Raw PDTOn 21/25 | J15: 0825GC105020L2125P | K15: =VLOOKUP(J15,master!B:D,3,0) -> VA PDTO IQF T NB 21/25 5X2LB
C16: 16/20 | D16: pdto | E16: 75 | F16: kgs | I16: Raw PDTOn 16/20 | J16: 0825GC105020L1620P | K16: =VLOOKUP(J16,master!B:D,3,0) -> VA PDTO IQF T NB 16/20 5X2LB
C17: 21/25 | D17: pdto | E17: 50 | F17: kgs | I17: Raw PDTOn 26/30 | J17: 0825GC105020L2630P | K17: =VLOOKUP(J17,master!B:D,3,0) -> VA PDTO IQF T NB 26/30 5X2LB
C18: 21/30 | D18: pdto | E18: 24 | F18: kgs | I18: Raw PDTOff 51/60 | J18: 0826VC105020L5160P | K18: =VLOOKUP(J18,master!B:D,3,0) -> VA PDTL IQF T NB 51/60 5X2LB
C19: 21/30 | D19: pd | E19: 16 | F19: kgs | G19: - | I19: Raw PDTOff 26/30 | J19: 0826VC105020L2630P | K19: =VLOOKUP(J19,master!B:D,3,0) -> VA PDTL IQF T NB 26/30 5X2LB
C20: 31/40 | D20: pd | E20: 120 | F20: kgs | I20: Raw PDTOff 41/50 | J20: 0826VC105020L4150P | K20: =VLOOKUP(J20,master!B:D,3,0) -> VA PDTL IQF T NB 41/50 5X2LB
C21: 41/50 | D21: pd. | E21: 140 | F21: kgs | I21: Raw PDTOff 31/40 | J21: 0826VC105020L3140P | K21: =VLOOKUP(J21,master!B:D,3,0) -> VA PDTL IQF T NB 31/40 5X2LB
C22: 51/60 | D22: pd. | E22: 100 | F22: kgs
